proteingym/__init__.py
proteingym/merge.py
proteingym/merge_supervised.py
proteingym/performance_DMS_benchmarks.py
proteingym/performance_DMS_supervised_benchmarks.py
proteingym-1.3.dist-info/licenses/LICENSE
proteingym-1.3.dist-info/METADATA
proteingym-1.3.dist-info/WHEEL
proteingym-1.3.dist-info/top_level.txt
proteingym-1.3.dist-info/RECORD
