Metadata-Version: 2.4
Name: proteingym
Version: 1.3
Summary: ProteinGym: Large-Scale Benchmarks for Protein Design and Fitness Prediction
Home-page: https://github.com/OATML-Markslab/ProteinGym
Author: OATML-Markslab
License: MIT
License-File: LICENSE
Dynamic: author
Dynamic: description
Dynamic: description-content-type
Dynamic: home-page
Dynamic: license
Dynamic: license-file
Dynamic: summary
